xmlclasses/__init__.py
xmlclasses/base_types.py
xmlclasses/converters.py
xmlclasses/error_handlers.py
xmlclasses/py.typed
xmlclasses/utils.py
xmlclasses/xml_elementTree_utils.py
xmlclasses-0.2.0.dist-info/METADATA
xmlclasses-0.2.0.dist-info/WHEEL
xmlclasses-0.2.0.dist-info/RECORD
