Metadata-Version: 2.4
Name: xmlclasses
Version: 0.2.0
Summary: Simple, fast, lightweight xml parser and validator defined by classes.
Project-URL: repository, https://github.com/tacozMacleo/xmlClasses
Project-URL: Bug Tracker, https://github.com/tacozMacleo/xmlClasses/issues
Author-email: Michael Bach Kristensen <tacoz666@gmail.com>
Requires-Python: >=3.11
